{"loss": 0.4404858025062622, "epoch": 0, "timestamp": 1723633923, "checkpoint_dir_name": null, "done": false, "training_iteration": 1, "trial_id": "f79e0_00000", "date": "2024-08-14_13-12-03", "time_this_iter_s": 27.23509407043457, "time_total_s": 27.23509407043457, "pid": 331068, "hostname": "turing", "node_ip": "192.168.209.37", "config": {}, "time_since_restore": 27.23509407043457, "iterations_since_restore": 1}
{"loss": 0.2841960231252311, "epoch": 1, "timestamp": 1723633939, "checkpoint_dir_name": null, "done": false, "training_iteration": 2, "trial_id": "f79e0_00000", "date": "2024-08-14_13-12-19", "time_this_iter_s": 15.749001741409302, "time_total_s": 42.98409581184387, "pid": 331068, "hostname": "turing", "node_ip": "192.168.209.37", "config": {}, "time_since_restore": 42.98409581184387, "iterations_since_restore": 2}
{"loss": 0.30610017861864613, "epoch": 2, "timestamp": 1723633954, "checkpoint_dir_name": null, "done": false, "training_iteration": 3, "trial_id": "f79e0_00000", "date": "2024-08-14_13-12-34", "time_this_iter_s": 15.831968307495117, "time_total_s": 58.81606411933899, "pid": 331068, "hostname": "turing", "node_ip": "192.168.209.37", "config": {}, "time_since_restore": 58.81606411933899, "iterations_since_restore": 3}
{"loss": 0.26291687703575317, "epoch": 3, "timestamp": 1723633970, "checkpoint_dir_name": null, "done": false, "training_iteration": 4, "trial_id": "f79e0_00000", "date": "2024-08-14_13-12-50", "time_this_iter_s": 15.792582988739014, "time_total_s": 74.608647108078, "pid": 331068, "hostname": "turing", "node_ip": "192.168.209.37", "config": {}, "time_since_restore": 74.608647108078, "iterations_since_restore": 4}
{"loss": 0.22586845972177522, "epoch": 4, "timestamp": 1723633986, "checkpoint_dir_name": null, "done": false, "training_iteration": 5, "trial_id": "f79e0_00000", "date": "2024-08-14_13-13-06", "time_this_iter_s": 15.905284404754639, "time_total_s": 90.51393151283264, "pid": 331068, "hostname": "turing", "node_ip": "192.168.209.37", "config": {}, "time_since_restore": 90.51393151283264, "iterations_since_restore": 5}
{"loss": 0.14817241601033299, "epoch": 5, "timestamp": 1723634002, "checkpoint_dir_name": null, "done": false, "training_iteration": 6, "trial_id": "f79e0_00000", "date": "2024-08-14_13-13-22", "time_this_iter_s": 15.860432624816895, "time_total_s": 106.37436413764954, "pid": 331068, "hostname": "turing", "node_ip": "192.168.209.37", "config": {}, "time_since_restore": 106.37436413764954, "iterations_since_restore": 6}
{"loss": 0.20078425334682515, "epoch": 6, "timestamp": 1723634018, "checkpoint_dir_name": null, "done": false, "training_iteration": 7, "trial_id": "f79e0_00000", "date": "2024-08-14_13-13-38", "time_this_iter_s": 16.07406735420227, "time_total_s": 122.4484314918518, "pid": 331068, "hostname": "turing", "node_ip": "192.168.209.37", "config": {}, "time_since_restore": 122.4484314918518, "iterations_since_restore": 7}
{"loss": 0.17704141250655886, "epoch": 7, "timestamp": 1723634034, "checkpoint_dir_name": null, "done": false, "training_iteration": 8, "trial_id": "f79e0_00000", "date": "2024-08-14_13-13-54", "time_this_iter_s": 15.984409809112549, "time_total_s": 138.43284130096436, "pid": 331068, "hostname": "turing", "node_ip": "192.168.209.37", "config": {}, "time_since_restore": 138.43284130096436, "iterations_since_restore": 8}
